ratekit/__init__.py
ratekit/data/__init__.py
ratekit/db/__init__.py
ratekit/func/__init__.py
ratekit-0.0.1.dist-info/METADATA
ratekit-0.0.1.dist-info/WHEEL
ratekit-0.0.1.dist-info/licenses/LICENSE
ratekit-0.0.1.dist-info/RECORD
