Metadata-Version: 2.3
Name: ratekit
Version: 0.0.1
Summary: Python package for the processing and classification of billing tickets.
Project-URL: Homepage, https://github.com/nommu-moose/ratekit
Project-URL: Bug Tracker, https://github.com/nommu-moose/ratekit/issues
Author-email: Cameron Fazakerley <moose@nommumail.co.uk>
License:                     GNU GENERAL PUBLIC LICENSE
License-File: LICENSE
Classifier: License :: OSI Approved :: GNU General Public License v3 (GPLv3)
Classifier: Operating System :: OS Independent
Classifier: Programming Language :: Python :: 3
Requires-Python: >=3.8
